{"cameraMode":{"drawMode":0,"name":"Shaded","section":"Shading Mode"},"sceneLighting":true,"audioPlay":false,"sceneViewState":{"showFog":true,"showMaterialUpdate":false,"showSkybox":true,"showFlares":true,"showImageEffects":true,"showParticleSystems":true},"in2DMode":false,"pivot":{"x":1.9326202869415284,"y":-18.9805965423584,"z":-8.278335571289063},"rotation":{"x":0.31426385045051577,"y":0.027051188051700593,"z":-0.008948327973484993,"w":0.9489256143569946},"size":47.46673583984375,"orthographic":false}